python_kit/__init__.py
python_kit/app.py
python_kit/app_v2.py
PythonGRPCKit-0.0.3.dist-info/METADATA
PythonGRPCKit-0.0.3.dist-info/WHEEL
PythonGRPCKit-0.0.3.dist-info/top_level.txt
PythonGRPCKit-0.0.3.dist-info/RECORD
